zredis.py
zredis-0.1.0.dist-info/LICENSE
zredis-0.1.0.dist-info/METADATA
zredis-0.1.0.dist-info/WHEEL
zredis-0.1.0.dist-info/top_level.txt
zredis-0.1.0.dist-info/RECORD
